cost_estimation_analyser/__init__.py
cost_estimation_analyser/cost_estimation_analyser.py
cost_estimation_analyser-0.1.1.dist-info/METADATA
cost_estimation_analyser-0.1.1.dist-info/WHEEL
cost_estimation_analyser-0.1.1.dist-info/top_level.txt
cost_estimation_analyser-0.1.1.dist-info/RECORD
