Metadata-Version: 2.1
Name: cost_estimation_analyser
Version: 0.1.1
Summary: It is a reusable estimated cost analyser library for insurance claim estimation analyser tool
Author: Deepak
License: MIT
Classifier: Programming Language :: Python :: 3
Classifier: License :: OSI Approved :: MIT License
Classifier: Operating System :: OS Independent
Requires-Python: >=3.6
